odoo8_addon_stock_operation_type_location-8.0.1.0.0-py2.7-nspkg.pth
odoo8_addon_stock_operation_type_location-8.0.1.0.0.dist-info/top_level.txt
odoo8_addon_stock_operation_type_location-8.0.1.0.0.dist-info/WHEEL
odoo8_addon_stock_operation_type_location-8.0.1.0.0.dist-info/RECORD
odoo8_addon_stock_operation_type_location-8.0.1.0.0.dist-info/metadata.json
odoo8_addon_stock_operation_type_location-8.0.1.0.0.dist-info/DESCRIPTION.rst
odoo8_addon_stock_operation_type_location-8.0.1.0.0.dist-info/METADATA
odoo8_addon_stock_operation_type_location-8.0.1.0.0.dist-info/namespace_packages.txt
odoo_addons/stock_operation_type_location/__openerp__.py
odoo_addons/stock_operation_type_location/__init__.py
odoo_addons/stock_operation_type_location/README.rst
odoo_addons/stock_operation_type_location/models/stock_move.py
odoo_addons/stock_operation_type_location/models/__init__.py
odoo_addons/stock_operation_type_location/models/stock_picking_type.py
odoo_addons/stock_operation_type_location/views/stock_picking_type_view.xml
odoo_addons/stock_operation_type_location/tests/test_onchange_location.py
odoo_addons/stock_operation_type_location/tests/__init__.py
odoo_addons/stock_operation_type_location/static/description/icon.png
